dubhe/__init__.py
dubhe/auth/__init__.py
dubhe/auth/auth.py
dubhe/auth/authpo.py
dubhe/cli/__init__.py
dubhe/cli/auth_cli.py
dubhe/cli/cli.py
dubhe/cli/dataset_cli.py
dubhe/cli/image_cli.py
dubhe/cli/sys_cli.py
dubhe/cli/workspace_cli.py
dubhe/dataset/__init__.py
dubhe/dataset/dataset.py
dubhe/dataset/dataset_file.py
dubhe/dataset/datasetpo.py
dubhe/image/__init__.py
dubhe/image/context.py
dubhe/image/image.py
dubhe/service/__init__.py
dubhe/service/context.py
dubhe/service/dataset.py
dubhe/service/out_dataset.py
dubhe/service/pipeline.py
dubhe/service/run.py
dubhe/utils/BaseModel.py
dubhe/utils/__init__.py
dubhe/utils/config.py
dubhe/utils/download.py
dubhe/utils/http_help.py
dubhe/utils/propertypo.py
dubhe/utils/time.py
dubhe/workspace/__init__.py
dubhe/workspace/workspace.py
dubhe-0.1.3.dist-info/LICENSE
dubhe-0.1.3.dist-info/METADATA
dubhe-0.1.3.dist-info/WHEEL
dubhe-0.1.3.dist-info/entry_points.txt
dubhe-0.1.3.dist-info/top_level.txt
dubhe-0.1.3.dist-info/zip-safe
dubhe-0.1.3.dist-info/RECORD
