Metadata-Version: 2.1
Name: dubhe
Version: 0.1.3
Summary: TCL AI platform, algorithm image develop cli tool
Home-page: https://github.com/xylophone21/dubhe_cli
Author: lihui
Author-email: lihui02@tcl.com
License: MIT
Keywords: dubhe
Platform: UNKNOWN
Requires-Dist: tqdm (>=4.51.0)
Requires-Dist: mako (>=1.1.3)
Requires-Dist: requests (>=2.22.0)
Requires-Dist: dubhe (>=0.1.0)
Requires-Dist: peewee (>=3.14.0)
